AUTHORS
MANIFEST.in
README.rst
UNLICENSE
setup.py
assetgen/__init__.py
assetgen/main.py
assetgen/version.py
assetgen.egg-info/PKG-INFO
assetgen.egg-info/SOURCES.txt
assetgen.egg-info/dependency_links.txt
assetgen.egg-info/entry_points.txt
assetgen.egg-info/requires.txt
assetgen.egg-info/top_level.txt
assetgen.egg-info/zip-safe