Metadata-Version: 1.0
Name: assetgen
Version: 0.3.5
Summary: Asset generator for modern web app development
Home-page: https://github.com/tav/assetgen
Author: tav
Author-email: tav@espians.com
License: Public Domain
Keywords: assets,javascript,css,coffeescript,sass,typescript,less,lessjs,roole,scss,stylus,source maps,i18n
Platform: UNKNOWN
Classifier: Development Status :: 5 - Production/Stable
Classifier: Environment :: Web Environment
Classifier: Intended Audience :: Developers
Classifier: License :: Public Domain
Classifier: Operating System :: OS Independent
Classifier: Programming Language :: Python
Classifier: Topic :: Text Processing
Classifier: Topic :: Utilities
